_test_warn.py
sc_ssGSEA/Expression.py
sc_ssGSEA/__init__.py
sc_ssGSEA/load_seurat.R
sc_ssGSEA/sc_ssGSEA.py
sc_ssgsea-1.2.7.dist-info/LICENSE
sc_ssgsea-1.2.7.dist-info/METADATA
sc_ssgsea-1.2.7.dist-info/WHEEL
sc_ssgsea-1.2.7.dist-info/top_level.txt
sc_ssgsea-1.2.7.dist-info/RECORD
