Metadata-Version: 2.2
Name: sc_ssGSEA
Version: 1.2.7
Summary: A Python package for performing gene set enrichment analysis on single cell clusters.
Author: John Jun
Author-email: "Alexander T. Wenzel" <atwenzel@ucsd.edu>
Requires-Python: >=3.10.0
License-File: LICENSE
Requires-Dist: pandas>=2.2.0
Requires-Dist: numpy>=1.26.0
Requires-Dist: scipy>=1.11.0
Requires-Dist: typing-extensions>=4.12.0
Requires-Dist: scanpy[leiden]>=1.11.0
